<?xml version="1.0" ?>
<world>
	<obstacle>
		<filename>models/objects/experiment_table.xml</filename>
		<transform>
			<fullTransform>(+0.846607 +0.00780908 -0.0116646 -0.532033)[+88.2956 -631.682 -49.52]</fullTransform>
		</transform>
	</obstacle>
	<obstacle>
		<filename>models/objects/experiment_table.xml</filename>
		<transform>
			<fullTransform>(+0.846607 +0.00780908 -0.0116646 -0.532033)[+88.2956 -631.682 -109.52]</fullTransform>
		</transform>
	</obstacle>
	<obstacle>
		<filename>models/objects/chair.xml</filename>
		<transform>
			<fullTransform>(+0.00386562 -0.209544 +0.97778 +0.00474608)[+78.9099 -1014.36 +657.675]</fullTransform>
		</transform>
	</obstacle>
	<graspableBody>
		<filename>models/object_database/block_50.xml</filename>
		<transform>
			<fullTransform>(-0.00348749 -0.205898 +0.977368 +0.0484264)[+392.481 -326.145 +92.7166]</fullTransform>
		</transform>
	</graspableBody>
	<graspableBody>
		<filename>models/object_database/block_64.xml</filename>
		<transform>
			<fullTransform>(-0.00289424 -0.217851 +0.974774 +0.0484655)[+202.712 -339.905 +91.4545]</fullTransform>
		</transform>
	</graspableBody>
	<graspableBody>
		<filename>models/object_database/block_64.xml</filename>
		<transform>
			<fullTransform>(-0.00320644 -0.211566 +0.976157 +0.0484458)[+304.668 -465.615 +114.829]</fullTransform>
		</transform>
	</graspableBody>
	<graspableBody>
		<filename>models/objects/monitor.xml</filename>
		<transform>
			<fullTransform>(+0.365155 -0.388308 -0.578295 +0.61762)[-82.9527 -366.875 +87.6846]</fullTransform>
		</transform>
	</graspableBody>
	<robot>
		<filename>models/robots/MicoGripper/MicoGripper.xml</filename>
		<dofValues>+0.905708 +1.06572 +0 +0 </dofValues>
		<transform>
			<fullTransform>(-0.0165886 +0.523838 -0.850178 -0.0501643)[-1170.54 +47.761 +364.056]</fullTransform>
		</transform>
	</robot>
	<camera>
		<position>+278.383 -1359.6 -294.912</position>
		<orientation>-0.167304 +0.780584 -0.588669 +0.127148</orientation>
		<focalDistance>+671.457</focalDistance>
	</camera>
</world>
